odoo10_addon_stock_orderpoint_manual_procurement_uom-10.0.1.0.0-py2.7-nspkg.pth
odoo/addons/stock_orderpoint_manual_procurement_uom/README.rst
odoo/addons/stock_orderpoint_manual_procurement_uom/__init__.py
odoo/addons/stock_orderpoint_manual_procurement_uom/__manifest__.py
odoo/addons/stock_orderpoint_manual_procurement_uom/models/__init__.py
odoo/addons/stock_orderpoint_manual_procurement_uom/models/stock_warehouse_orderpoint.py
odoo/addons/stock_orderpoint_manual_procurement_uom/static/description/icon.png
odoo/addons/stock_orderpoint_manual_procurement_uom/tests/__init__.py
odoo/addons/stock_orderpoint_manual_procurement_uom/tests/test_stock_orderpoint_manual_procurement.py
odoo/addons/stock_orderpoint_manual_procurement_uom/wizards/__init__.py
odoo/addons/stock_orderpoint_manual_procurement_uom/wizards/make_procurement_orderpoint.py
odoo10_addon_stock_orderpoint_manual_procurement_uom-10.0.1.0.0.dist-info/DESCRIPTION.rst
odoo10_addon_stock_orderpoint_manual_procurement_uom-10.0.1.0.0.dist-info/METADATA
odoo10_addon_stock_orderpoint_manual_procurement_uom-10.0.1.0.0.dist-info/RECORD
odoo10_addon_stock_orderpoint_manual_procurement_uom-10.0.1.0.0.dist-info/WHEEL
odoo10_addon_stock_orderpoint_manual_procurement_uom-10.0.1.0.0.dist-info/metadata.json
odoo10_addon_stock_orderpoint_manual_procurement_uom-10.0.1.0.0.dist-info/namespace_packages.txt
odoo10_addon_stock_orderpoint_manual_procurement_uom-10.0.1.0.0.dist-info/top_level.txt
