Metadata-Version: 2.0
Name: odoo10-addon-stock-orderpoint-manual-procurement-uom
Version: 10.0.1.0.0
Summary: Glue module for stock_orderpoint_uom and stock_orderpoint_manual_procurement
Home-page: https://github.com/OCA/stock-logistics-warehouse
Author: Eficent, Odoo Community Association (OCA)
Author-email: support@odoo-community.org
License: AGPL-3
Platform: UNKNOWN
Classifier: Programming Language :: Python
Classifier: Framework :: Odoo
Classifier: License :: OSI Approved :: GNU Affero General Public License v3
Requires-Python: ~=2.7
Requires-Dist: odoo (<10.1dev,>=10.0)
Requires-Dist: odoo10-addon-stock-orderpoint-manual-procurement
Requires-Dist: odoo10-addon-stock-orderpoint-uom
